[
    {
        "id": 0,
        "gamertag":"vrustidge0",
        "firstname":"Vernon",
        "lastname":"Rustidge",
        "answers": ["A"]
    },
    {
        "id": 1,
        "gamertag":"hsimonett1",
        "firstname":"Harbert",
        "lastname":"Simonett",
        "answers": ["B"]
    },
    {
        "id": 2,
        "gamertag":"bgile2",
        "firstname":"Blancha",
        "lastname":"Gile",
        "answers": ["A"]
    },
    {
        "id": 3,
        "gamertag":"dborghese3",
        "firstname":"Dael",
        "lastname":"Borghese",
        "answers": ["B"]
    },
    {
        "id": 4,
        "gamertag":"rroxburgh4",
        "firstname":"Robyn",
        "lastname":"Roxburgh",
        "answers": ["A"]
    },
    {
        "id": 5,
        "gamertag":"cstocky5",
        "firstname":"Chad",
        "lastname":"Stocky",
        "answers": ["A"]
    },
    {
        "id": 6,
        "gamertag":"ewishkar6",
        "firstname":"Evvy",
        "lastname":"Wishkar",
        "answers": ["A"]
    },
    {
        "id": 7,
        "gamertag":"ggarlett7",
        "firstname":"Gallard",
        "lastname":"Garlett",
        "answers": ["D"]
    },
    {
        "id": 8,
        "gamertag":"cdrejer8",
        "firstname":"Colan",
        "lastname":"Drejer",
        "answers": ["D"]
    },
    {
        "id": 9,
        "gamertag":"btomashov9",
        "firstname":"Bartholomew",
        "lastname":"Tomashov",
        "answers": ["C"]
    }
]